LICENSE
MANIFEST.in
README.md
pyproject.toml
requirements.txt
setup.py
tests/test_process.py
tests/test_server.py
tests/test_thread.py
zerofun/__init__.py
zerofun/client.py
zerofun/pool.py
zerofun/proc_server.py
zerofun/process.py
zerofun/server.py
zerofun/sockets.py
zerofun/thread.py
zerofun/utils.py
zerofun.egg-info/PKG-INFO
zerofun.egg-info/SOURCES.txt
zerofun.egg-info/dependency_links.txt
zerofun.egg-info/requires.txt
zerofun.egg-info/top_level.txt