Metadata-Version: 2.1
Name: zerofun
Version: 2.3.1
Summary: Remote function calls for array data using ZMQ
Home-page: http://github.com/danijar/zerofun
Author: Danijar Hafner
Author-email: mail@danijar.com
Classifier: Intended Audience :: Science/Research
Classifier: License :: OSI Approved :: MIT License
Classifier: Programming Language :: Python :: 3
License-File: LICENSE
